LICENSE
MANIFEST.in
README.rst
setup.cfg
setup.py
django_formset_js.egg-info/PKG-INFO
django_formset_js.egg-info/SOURCES.txt
django_formset_js.egg-info/dependency_links.txt
django_formset_js.egg-info/not-zip-safe
django_formset_js.egg-info/requires.txt
django_formset_js.egg-info/top_level.txt
djangoformsetjs/__init__.py
djangoformsetjs/utils.py
djangoformsetjs/static/js/jquery.formset.js
djangoformsetjs/static/js/jquery.formset.min.js
djangoformsetjs/static/js/jquery.formset.min.js.map
djangoformsetjs/templatetags/__init__.py
djangoformsetjs/templatetags/formset_tags.py