Metadata-Version: 1.1
Name: django-formset-js
Version: 0.5.0
Summary: Extend Django formsets with JavaScript
Home-page: https://bitbucket.org/tim_heap/django-formset-js
Author: Tim Heap
Author-email: tim@timheap.me
License: BSD
Platform: UNKNOWN
Classifier: Environment :: Web Environment
Classifier: Intended Audience :: Developers
Classifier: Operating System :: OS Independent
Classifier: Programming Language :: Python
Classifier: Framework :: Django
Classifier: License :: OSI Approved :: BSD License
